setup.py
cyberoam_candy/__init__.py
cyberoam_candy/cyberoam_candy.py
cyberoam_candy.egg-info/PKG-INFO
cyberoam_candy.egg-info/SOURCES.txt
cyberoam_candy.egg-info/dependency_links.txt
cyberoam_candy.egg-info/not-zip-safe
cyberoam_candy.egg-info/top_level.txt