Metadata-Version: 1.0
Name: cyberoam-candy
Version: 0.23
Summary: Basic Cyberoam login client. Command line interface.
Home-page: http://github.com/bhavul/cyberoam-candy
Author: Bhavul Gauri
Author-email: bhavul93@gmail.com
License: MIT
Platform: UNKNOWN
